codebase_extractor/__init__.py
codebase_extractor/cli.py
codebase_extractor/config.py
codebase_extractor/file_handler.py
codebase_extractor/main_logic.py
codebase_extractor/ui.py
codebase_extractor-1.1.1.dist-info/licenses/LICENCE
codebase_extractor-1.1.1.dist-info/METADATA
codebase_extractor-1.1.1.dist-info/WHEEL
codebase_extractor-1.1.1.dist-info/entry_points.txt
codebase_extractor-1.1.1.dist-info/top_level.txt
codebase_extractor-1.1.1.dist-info/RECORD
