Metadata-Version: 2.4
Name: codebase-extractor
Version: 1.1.1
Summary: A CLI tool to extract project source code into structured Markdown files for LLM & AI context.
Author: Lukasz Lekowski
Project-URL: Homepage, https://github.com/lukaszlekowski/codebase-extractor
Project-URL: Bug Tracker, https://github.com/lukaszlekowski/codebase-extractor/issues
Classifier: Programming Language :: Python :: 3
Classifier: License :: OSI Approved :: MIT License
Classifier: Operating System :: OS Independent
Classifier: Topic :: Software Development :: Documentation
Classifier: Topic :: Utilities
Requires-Python: >=3.9
License-File: LICENCE
Requires-Dist: questionary
Requires-Dist: halo
Requires-Dist: termcolor
Dynamic: license-file
